setup.cfg
setup.py
Flask_JWT_Simple.egg-info/PKG-INFO
Flask_JWT_Simple.egg-info/SOURCES.txt
Flask_JWT_Simple.egg-info/dependency_links.txt
Flask_JWT_Simple.egg-info/not-zip-safe
Flask_JWT_Simple.egg-info/requires.txt
Flask_JWT_Simple.egg-info/top_level.txt
flask_jwt_simple/__init__.py
flask_jwt_simple/config.py
flask_jwt_simple/default_callbacks.py
flask_jwt_simple/exceptions.py
flask_jwt_simple/jwt_manager.py
flask_jwt_simple/utils.py
flask_jwt_simple/view_decorators.py