Metadata-Version: 1.1
Name: Flask-JWT-Simple
Version: 0.0.2
Summary: Simple JWT integration with Flask
Home-page: https://github.com/vimalloc/flask-jwt-simple
Author: Landon Gilbert-Bland
Author-email: landogbland@gmail.com
License: MIT
Keywords: flask,jwt,json web token
Platform: any
Classifier: Development Status :: 4 - Beta
Classifier: Environment :: Web Environment
Classifier: Intended Audience :: Developers
Classifier: License :: OSI Approved :: MIT License
Classifier: Operating System :: OS Independent
Classifier: Programming Language :: Python
Classifier: Programming Language :: Python :: 2.7
Classifier: Programming Language :: Python :: 3
Classifier: Programming Language :: Python :: 3.3
Classifier: Programming Language :: Python :: 3.4
Classifier: Programming Language :: Python :: 3.5
Classifier: Programming Language :: Python :: 3.6
Classifier: Topic :: Internet :: WWW/HTTP :: Dynamic Content
Classifier: Topic :: Software Development :: Libraries :: Python Modules
